logxide-0.1.2.dist-info/METADATA
logxide-0.1.2.dist-info/WHEEL
logxide-0.1.2.dist-info/licenses/LICENSE
logxide/__init__.py
logxide/__init__.pyi
logxide/compat_functions.py
logxide/compat_handlers.py
logxide/logger_wrapper.py
logxide/logxide.pypy310-pp73-arm-linux-gnu.so
logxide/module_system.py
logxide/py.typed
logxide/sentry_integration.py
logxide-0.1.2.dist-info/RECORD
