Metadata-Version: 2.4
Name: logxide
Version: 0.1.2
Classifier: Development Status :: 4 - Beta
Classifier: Intended Audience :: Developers
Classifier: License :: OSI Approved :: MIT License
Classifier: Operating System :: OS Independent
Classifier: Programming Language :: Python :: 3
Classifier: Programming Language :: Python :: 3.9
Classifier: Programming Language :: Python :: 3.10
Classifier: Programming Language :: Python :: 3.11
Classifier: Programming Language :: Python :: 3.12
Classifier: Programming Language :: Python :: 3.13
Classifier: Programming Language :: Rust
Classifier: Topic :: Software Development :: Libraries :: Python Modules
Classifier: Topic :: System :: Logging
Classifier: Topic :: System :: Systems Administration
Classifier: Typing :: Typed
Requires-Dist: sentry-sdk>=1.40.0 ; extra == 'sentry'
Requires-Dist: pytest ; extra == 'dev'
Requires-Dist: pytest-cov ; extra == 'dev'
Requires-Dist: pyright ; extra == 'dev'
Requires-Dist: ruff ; extra == 'dev'
Requires-Dist: pre-commit ; extra == 'dev'
Requires-Dist: maturin>=1.0,<2.0 ; extra == 'dev'
Requires-Dist: mkdocs ; extra == 'dev'
Requires-Dist: mkdocs-material ; extra == 'dev'
Requires-Dist: mkdocstrings[python] ; extra == 'dev'
Requires-Dist: pymdown-extensions ; extra == 'dev'
Requires-Dist: django>=4.2.23 ; extra == 'dev'
Requires-Dist: fastapi>=0.116.1 ; extra == 'dev'
Requires-Dist: flask>=3.1.1 ; extra == 'dev'
Requires-Dist: flask-sqlalchemy>=3.1.1 ; extra == 'dev'
Requires-Dist: httpx>=0.28.1 ; extra == 'dev'
Requires-Dist: uvicorn>=0.35.0 ; extra == 'dev'
Requires-Dist: sentry-sdk>=1.40.0 ; extra == 'dev'
Provides-Extra: sentry
Provides-Extra: dev
License-File: LICENSE
Summary: High-performance, Rust-powered drop-in replacement for Python's logging module
Keywords: logging,rust,async,performance,drop-in-replacement,high-performance,thread-safe,structured-logging
Author-email: Indosaram <freedomzero91@gmail.com>
Maintainer-email: Indosaram <freedomzero91@gmail.com>
License: MIT
Requires-Python: >=3.9
Project-URL: Homepage, https://github.com/Indosaram/logxide
Project-URL: Repository, https://github.com/Indosaram/logxide
Project-URL: Documentation, https://Indosaram.readthedocs.io/logxide
Project-URL: Bug Tracker, https://github.com/Indosaram/logxide/issues
Project-URL: Changelog, https://github.com/Indosaram/logxide/blob/main/CHANGELOG.md
Project-URL: Source Code, https://github.com/Indosaram/logxide
